Workbook

Sheet Cover
B2: Bangladesh District Investment Attractiveness Index (BDIAI)
B3: Full Data, Methodology, and Ranking Workbook
B5: Author: Ahmed Safwan Sajid
B6: Prepared for: May International Trade Services Limited
B7: Companion file to: BDIAI_Research_Report.docx
B8: Date: July 2026
B10: © 2026 Ahmed Safwan Sajid. All Rights Reserved. Intellectual Property of the Author.
B12: This workbook is the intellectual property of the author. It may not be copied, redistributed, or reproduced, in whole or in part, without the author's express permission.
B15: Sheet Guide
B16: Cover — This page.
B17: Methodology — Indicators, weights, scoring approach, and the composite-score formula, explained in full.
B18: Formula Guide — Plain-language explanation of every formula type used in this workbook, with a worked example.
... B23: References — Complete numbered reference list (30 sources).

Sheet Methodology
B2: Bangladesh District Investment Attractiveness Index (BDIAI)
B3: Index Methodology & Scoring Framework
B5: 1. District Selection
B6: 20 districts selected on an economic/industrial-hub basis (strongest data availability), while retaining at least one district per division. See 'Rankings' sheet for the full list.
B8: 2. Indicators & Weights (INPUT CELLS — edit D10:D18 to re-run the model)
B9: Indicator | C9: Rationale | D9: Weight
B10: Seaport/Airport Proximity & Multimodal Connectivity | C10: Logistics cost is often the binding constraint on industrial siting in Bangladesh. | D10: 0.15
B11: EPZ / Economic Zone / Industrial Park Presence | C11: Direct proxy for state-backed / large-scale investment infrastructure. | D11: 0.15
B12: Power & Gas Availability / Reliability | C12: Repeatedly cited by manufacturers as the top operational risk. | D12: 0.15
B13: Labor Force Availability & Wage Competitiveness | C13: Core input cost and availability for industrial investment. | D13: 0.12
B14: Literacy Rate & Technical Education Infrastructure | C14: Skilled-labor pipeline for higher-value investment. | D14: 0.08
B15: Banking & Financial Institution Presence | C15: Access to trade finance and working capital. | D15: 0.1
B16: Broadband & Mobile Network Coverage | C16: Increasingly material for logistics, fintech, and back-office operations. | D16: 0.08
B17: Existing Industrial Base (Major Industries Present) | C17: Agglomeration effects and existing supplier ecosystems. | D17: 0.1
B18: Recent Public/Private Investment Momentum | C18: Forward-looking signal, not just static endowment. | D18: 0.07
B19: TOTAL (must equal 100%) | D19: =SUM(D10:D18) -> 1
B21: 3. The Composite Score Formula, In Full
B22: For each district, the Composite Score is: Composite Score = (Connectivity x 15%) + (EPZ/Econ. Zone x 15%) + (Power/Gas Reliability x 15%) + (Labor Availability x 12%) + (Banking Density x 10%) + (Industrial Base x 10%) + (Literacy/Tech Ed x 8%) + (Broadband/Mobile x 8%) + (Investment Momentum x 7%) Each term is one indicator's 0-100 score multiplied by its weight (see column D above). The nine weighted terms are then added together (Excel's SUM function) to produce one Composite Score per district, on a 0-100 scale. Because every weight is a fixed share of the 0-100 scale and the weights sum to exactly 100%, the Composite Score itself is also always on a 0-100 scale, so districts can be compared directly. Districts are then placed in rank order using Excel's RANK function, which simply counts how many Composite Scores in the list are higher than a given district's score and returns that as its rank (rank 1 = highest score = most attractive). IMPORTANT LIMITATION: for three indicators (Power/Gas Reliability, Banking Density, Broadband/Mobile — 33% of total weight), no single authoritative district-wise public dataset was retrievable via general web search within this research session. Scores for these three indicators are evidence-based ANALYST ESTIMATES using documented proxies (see 'Data Basis Notes' sheet), not official statistics. This is flagged transparently, and recommended primary sources for follow-up verification are named in the notes. See the 'Formula Guide' sheet for a full worked numeric example and a plain-language explanation of every formula used in this workbook.
B33: © 2026 Ahmed Safwan Sajid. All Rights Reserved. Intellectual Property of the Author.

Sheet Formula Guide
B2: Formula Guide — Every Formula Used In This Workbook, Explained
B4: Where It's Used | C4: Formula (as written in the cell) | D4: Plain-Language Explanation
B5: 'Rankings' sheet, each indicator column (e.g. cell E3) | C5: =INDEX('Indicator Scores (0-100)'!C$3:C$22, MATCH($C3,'Indicator Scores (0-100)'!$B$3:$B$22,0)) * Methodology!D$10 | D5: This looks up the district named in column C of this row (e.g. 'Dhaka'), FINDS that exact district name in the 'Indicator Scores' sheet (MATCH), and PULLS that district's score for this specific indicator (INDEX) — rather than assuming the two sheets are in the same row order. It then multiplies that score by the indicator's weight, which is pulled directly from the Methodology sheet. This is deliberately more robust than a plain 'same row number' reference: if a district is ever added, removed, or reordered on the Indicator Scores sheet, this formula still finds the correct district by name instead of silently pulling the wrong row.
B6: 'Rankings' sheet, Composite Score column (e.g. cell N3) | C6: =SUM(E3:M3) | D6: Adds up the nine weighted indicator contributions calculated in that row (columns E through M) into one 0-100 Composite Score for the district.
B7: 'Rankings' sheet, Rank column (e.g. cell B3) | C7: =RANK(N3,$N$3:$N$22) | D7: Compares this district's Composite Score (N3) against every district's score in the full range ($N$3:$N$22, locked with $ so it doesn't shift when copied down) and returns its position — 1 for the highest score, 20 for the lowest. Excel's RANK function handles this automatically; no manual sorting is needed, and the rank updates live if any score or weight changes.
B8: 'Methodology' sheet, Total Weight cell (D19) | C8: =SUM(D10:D18) | D8: Adds the nine indicator weights together as a check. This should always read 100% — if it does not, the weights have been mis-entered and the Composite Score scale will no longer run cleanly from 0 to 100.
B10: Worked Example — Dhaka's Composite Score
B11: Dhaka's nine raw indicator scores (from the 'Indicator Scores' sheet) and the workbook's weights (from 'Methodology') combine as follows: Connectivity: 95 x 15% = 14.25 EPZ/Econ. Zone: 90 x 15% = 13.50 Power/Gas Reliability:85 x 15% = 12.75 Labor Availability: 90 x 12% = 10.80 Banking Density: 95 x 10% = 9.50 Industrial Base: 95 x 10% = 9.50 Literacy/Tech Ed: 90 x 8% = 7.20 Broadband/Mobile: 90 x 8% = 7.20 Investment Momentum: 70 x 7% = 4.90 -------- SUM = 89.60 <- Dhaka's Composite Score, and Rank 1 of 20 Every other district's score in the 'Rankings' sheet is calculated the same way, automatically, by the formulas above — this worked example exists purely so the calculation can be checked by hand without opening Excel.
B26: © 2026 Ahmed Safwan Sajid. All Rights Reserved. Intellectual Property of the Author.

Sheet Indicator Scores (0-100)
B1: District-Level Indicator Scores (0-100 scale; higher = more attractive)
B2: District | C2: Connectivity | D2: EPZ / Econ. Zone | E2: Power/Gas Reliability | F2: Labor Availability | G2: Literacy/Tech Ed. | H2: Banking Density | I2: Broadband/Mobile | J2: Industrial Base | K2: Investment Momentum
B3: Dhaka | C3: 95 | D3: 90 | E3: 85 | F3: 90 | G3: 90 | H3: 95 | I3: 90 | J3: 95 | K3: 70
B4: Gazipur | C4: 85 | D4: 85 | E4: 80 | F4: 95 | G4: 70 | H4: 75 | I4: 75 | J4: 95 | K4: 80
B5: Narayanganj | C5: 80 | D5: 75 | E5: 75 | F5: 85 | G5: 65 | H5: 75 | I5: 75 | J5: 85 | K5: 60
B6: Chattogram | C6: 100 | D6: 100 | E6: 85 | F6: 85 | G6: 70 | H6: 90 | I6: 80 | J6: 95 | K6: 85
B7: Cumilla | C7: 55 | D7: 80 | E7: 70 | F7: 70 | G7: 60 | H7: 65 | I7: 65 | J7: 70 | K7: 65
B8: Feni | C8: 70 | D8: 90 | E8: 75 | F8: 60 | G8: 60 | H8: 60 | I8: 60 | J8: 55 | K8: 90
B9: Cox's Bazar | C9: 75 | D9: 85 | E9: 70 | F9: 55 | G9: 50 | H9: 55 | I9: 55 | J9: 45 | K9: 90
B10: Narsingdi | C10: 65 | D10: 30 | E10: 65 | F10: 65 | G10: 55 | H10: 55 | I10: 60 | J10: 65 | K10: 55
B11: Munshiganj | C11: 70 | D11: 60 | E11: 70 | F11: 55 | G11: 60 | H11: 55 | I11: 60 | J11: 55 | K11: 75
B12: Tangail | C12: 55 | D12: 25 | E12: 60 | F12: 55 | G12: 50 | H12: 55 | I12: 55 | J12: 50 | K12: 45
B13: Bogura | C13: 50 | D13: 20 | E13: 55 | F13: 60 | G13: 60 | H13: 65 | I13: 60 | J13: 55 | K13: 60
B14: Rajshahi | C14: 45 | D14: 25 | E14: 40 | F14: 55 | G14: 65 | H14: 70 | I14: 65 | J14: 40 | K14: 40
... B22: Faridpur | C22: 60 | D22: 30 | E22: 60 | F22: 55 | G22: 55 | H22: 55 | I22: 55 | J22: 45 | K22: 60
B24: Blue values are analyst-assigned inputs based on documented evidence (see Source Log and Methodology sheets). Edit these cells to re-run the model with updated data — the 'Rankings' sheet looks up each district by NAME (not by row position), so scores can be edited, and rows re-sorted or added, without breaking any formula.
B26: © 2026 Ahmed Safwan Sajid. All Rights Reserved. Intellectual Property of the Author.

Sheet Rankings
B1: BDIAI Final Ranking (weighted composite score)
B2: Rank | C2: District | D2: Division | E2: Connectivity | F2: EPZ / Econ. Zone | G2: Power/Gas Reliability | H2: Labor Availability | I2: Literacy/Tech Ed. | J2: Banking Density | K2: Broadband/Mobile | L2: Industrial Base | M2: Investment Momentum | N2: Composite Score
B3: =RANK(N3,$N$3:$N$22) -> 1 | C3: Dhaka | D3: Dhaka | E3: =INDEX('Indicator Scores (0-100)'!C$3:C$22,MATCH($C3,'Indicator Scores (0-100)'!$B$3:$B$22,0))*Methodology!$D$10 -> 14.25 | F3: =INDEX('Indicator Scores (0-100)'!D$3:D$22,MATCH($C3,'Indicator Scores (0-100)'!$B$3:$B$22,0))*Methodology!$D$11 -> 13.5 | G3: =INDEX('Indicator Scores (0-100)'!E$3:E$22,MATCH($C3,'Indicator Scores (0-100)'!$B$3:$B$22,0))*Methodology!$D$12 -> 12.75 | H3: =INDEX('Indicator Scores (0-100)'!F$3:F$22,MATCH($C3,'Indicator Scores (0-100)'!$B$3:$B$22,0))*Methodology!$D$13 -> 10.8 | I3: =INDEX('Indicator Scores (0-100)'!G$3:G$22,MATCH($C3,'Indicator Scores (0-100)'!$B$3:$B$22,0))*Methodology!$D$14 -> 7.2 | J3: =INDEX('Indicator Scores (0-100)'!H$3:H$22,MATCH($C3,'Indicator Scores (0-100)'!$B$3:$B$22,0))*Methodology!$D$15 -> 9.5 | K3: =INDEX('Indicator Scores (0-100)'!I$3:I$22,MATCH($C3,'Indicator Scores (0-100)'!$B$3:$B$22,0))*Methodology!$D$16 -> 7.2 | L3: =INDEX('Indicator Scores (0-100)'!J$3:J$22,MATCH($C3,'Indicator Scores (0-100)'!$B$3:$B$22,0))*Methodology!$D$17 -> 9.5 | M3: =INDEX('Indicator Scores (0-100)'!K$3:K$22,MATCH($C3,'Indicator Scores (0-100)'!$B$3:$B$22,0))*Methodology!$D$18 -> 4.9 | N3: =SUM(E3:M3) -> 89.6
B4: =RANK(N4,$N$3:$N$22) -> 3 | C4: Gazipur | D4: Dhaka | E4: =INDEX('Indicator Scores (0-100)'!C$3:C$22,MATCH($C4,'Indicator Scores (0-100)'!$B$3:$B$22,0))*Methodology!$D$10 -> 12.75 | F4: =INDEX('Indicator Scores (0-100)'!D$3:D$22,MATCH($C4,'Indicator Scores (0-100)'!$B$3:$B$22,0))*Methodology!$D$11 -> 12.75 | G4: =INDEX('Indicator Scores (0-100)'!E$3:E$22,MATCH($C4,'Indicator Scores (0-100)'!$B$3:$B$22,0))*Methodology!$D$12 -> 12 | H4: =INDEX('Indicator Scores (0-100)'!F$3:F$22,MATCH($C4,'Indicator Scores (0-100)'!$B$3:$B$22,0))*Methodology!$D$13 -> 11.4 | I4: =INDEX('Indicator Scores (0-100)'!G$3:G$22,MATCH($C4,'Indicator Scores (0-100)'!$B$3:$B$22,0))*Methodology!$D$14 -> 5.6 | J4: =INDEX('Indicator Scores (0-100)'!H$3:H$22,MATCH($C4,'Indicator Scores (0-100)'!$B$3:$B$22,0))*Methodology!$D$15 -> 7.5 | K4: =INDEX('Indicator Scores (0-100)'!I$3:I$22,MATCH($C4,'Indicator Scores (0-100)'!$B$3:$B$22,0))*Methodology!$D$16 -> 6 | L4: =INDEX('Indicator Scores (0-100)'!J$3:J$22,MATCH($C4,'Indicator Scores (0-100)'!$B$3:$B$22,0))*Methodology!$D$17 -> 9.5 | M4: =INDEX('Indicator Scores (0-100)'!K$3:K$22,MATCH($C4,'Indicator Scores (0-100)'!$B$3:$B$22,0))*Methodology!$D$18 -> 5.6 | N4: =SUM(E4:M4) -> 83.1
B5: =RANK(N5,$N$3:$N$22) -> 4 | C5: Narayanganj | D5: Dhaka | E5: =INDEX('Indicator Scores (0-100)'!C$3:C$22,MATCH($C5,'Indicator Scores (0-100)'!$B$3:$B$22,0))*Methodology!$D$10 -> 12 | F5: =INDEX('Indicator Scores (0-100)'!D$3:D$22,MATCH($C5,'Indicator Scores (0-100)'!$B$3:$B$22,0))*Methodology!$D$11 -> 11.25 | G5: =INDEX('Indicator Scores (0-100)'!E$3:E$22,MATCH($C5,'Indicator Scores (0-100)'!$B$3:$B$22,0))*Methodology!$D$12 -> 11.25 | H5: =INDEX('Indicator Scores (0-100)'!F$3:F$22,MATCH($C5,'Indicator Scores (0-100)'!$B$3:$B$22,0))*Methodology!$D$13 -> 10.2 | I5: =INDEX('Indicator Scores (0-100)'!G$3:G$22,MATCH($C5,'Indicator Scores (0-100)'!$B$3:$B$22,0))*Methodology!$D$14 -> 5.2 | J5: =INDEX('Indicator Scores (0-100)'!H$3:H$22,MATCH($C5,'Indicator Scores (0-100)'!$B$3:$B$22,0))*Methodology!$D$15 -> 7.5 | K5: =INDEX('Indicator Scores (0-100)'!I$3:I$22,MATCH($C5,'Indicator Scores (0-100)'!$B$3:$B$22,0))*Methodology!$D$16 -> 6 | L5: =INDEX('Indicator Scores (0-100)'!J$3:J$22,MATCH($C5,'Indicator Scores (0-100)'!$B$3:$B$22,0))*Methodology!$D$17 -> 8.5 | M5: =INDEX('Indicator Scores (0-100)'!K$3:K$22,MATCH($C5,'Indicator Scores (0-100)'!$B$3:$B$22,0))*Methodology!$D$18 -> 4.2 | N5: =SUM(E5:M5) -> 76.1
B6: =RANK(N6,$N$3:$N$22) -> 2 | C6: Chattogram | D6: Chattogram | E6: =INDEX('Indicator Scores (0-100)'!C$3:C$22,MATCH($C6,'Indicator Scores (0-100)'!$B$3:$B$22,0))*Methodology!$D$10 -> 15 | F6: =INDEX('Indicator Scores (0-100)'!D$3:D$22,MATCH($C6,'Indicator Scores (0-100)'!$B$3:$B$22,0))*Methodology!$D$11 -> 15 | G6: =INDEX('Indicator Scores (0-100)'!E$3:E$22,MATCH($C6,'Indicator Scores (0-100)'!$B$3:$B$22,0))*Methodology!$D$12 -> 12.75 | H6: =INDEX('Indicator Scores (0-100)'!F$3:F$22,MATCH($C6,'Indicator Scores (0-100)'!$B$3:$B$22,0))*Methodology!$D$13 -> 10.2 | I6: =INDEX('Indicator Scores (0-100)'!G$3:G$22,MATCH($C6,'Indicator Scores (0-100)'!$B$3:$B$22,0))*Methodology!$D$14 -> 5.6 | J6: =INDEX('Indicator Scores (0-100)'!H$3:H$22,MATCH($C6,'Indicator Scores (0-100)'!$B$3:$B$22,0))*Methodology!$D$15 -> 9 | K6: =INDEX('Indicator Scores (0-100)'!I$3:I$22,MATCH($C6,'Indicator Scores (0-100)'!$B$3:$B$22,0))*Methodology!$D$16 -> 6.4 | L6: =INDEX('Indicator Scores (0-100)'!J$3:J$22,MATCH($C6,'Indicator Scores (0-100)'!$B$3:$B$22,0))*Methodology!$D$17 -> 9.5 | M6: =INDEX('Indicator Scores (0-100)'!K$3:K$22,MATCH($C6,'Indicator Scores (0-100)'!$B$3:$B$22,0))*Methodology!$D$18 -> 5.95 | N6: =SUM(E6:M6) -> 89.4
B7: =RANK(N7,$N$3:$N$22) -> 6 | C7: Cumilla | D7: Chattogram | E7: =INDEX('Indicator Scores (0-100)'!C$3:C$22,MATCH($C7,'Indicator Scores (0-100)'!$B$3:$B$22,0))*Methodology!$D$10 -> 8.25 | F7: =INDEX('Indicator Scores (0-100)'!D$3:D$22,MATCH($C7,'Indicator Scores (0-100)'!$B$3:$B$22,0))*Methodology!$D$11 -> 12 | G7: =INDEX('Indicator Scores (0-100)'!E$3:E$22,MATCH($C7,'Indicator Scores (0-100)'!$B$3:$B$22,0))*Methodology!$D$12 -> 10.5 | H7: =INDEX('Indicator Scores (0-100)'!F$3:F$22,MATCH($C7,'Indicator Scores (0-100)'!$B$3:$B$22,0))*Methodology!$D$13 -> 8.4 | I7: =INDEX('Indicator Scores (0-100)'!G$3:G$22,MATCH($C7,'Indicator Scores (0-100)'!$B$3:$B$22,0))*Methodology!$D$14 -> 4.8 | J7: =INDEX('Indicator Scores (0-100)'!H$3:H$22,MATCH($C7,'Indicator Scores (0-100)'!$B$3:$B$22,0))*Methodology!$D$15 -> 6.5 | K7: =INDEX('Indicator Scores (0-100)'!I$3:I$22,MATCH($C7,'Indicator Scores (0-100)'!$B$3:$B$22,0))*Methodology!$D$16 -> 5.2 | L7: =INDEX('Indicator Scores (0-100)'!J$3:J$22,MATCH($C7,'Indicator Scores (0-100)'!$B$3:$B$22,0))*Methodology!$D$17 -> 7 | M7: =INDEX('Indicator Scores (0-100)'!K$3:K$22,MATCH($C7,'Indicator Scores (0-100)'!$B$3:$B$22,0))*Methodology!$D$18 -> 4.55 | N7: =SUM(E7:M7) -> 67.2
B8: =RANK(N8,$N$3:$N$22) -> 5 | C8: Feni | D8: Chattogram | E8: =INDEX('Indicator Scores (0-100)'!C$3:C$22,MATCH($C8,'Indicator Scores (0-100)'!$B$3:$B$22,0))*Methodology!$D$10 -> 10.5 | F8: =INDEX('Indicator Scores (0-100)'!D$3:D$22,MATCH($C8,'Indicator Scores (0-100)'!$B$3:$B$22,0))*Methodology!$D$11 -> 13.5 | G8: =INDEX('Indicator Scores (0-100)'!E$3:E$22,MATCH($C8,'Indicator Scores (0-100)'!$B$3:$B$22,0))*Methodology!$D$12 -> 11.25 | H8: =INDEX('Indicator Scores (0-100)'!F$3:F$22,MATCH($C8,'Indicator Scores (0-100)'!$B$3:$B$22,0))*Methodology!$D$13 -> 7.2 | I8: =INDEX('Indicator Scores (0-100)'!G$3:G$22,MATCH($C8,'Indicator Scores (0-100)'!$B$3:$B$22,0))*Methodology!$D$14 -> 4.8 | J8: =INDEX('Indicator Scores (0-100)'!H$3:H$22,MATCH($C8,'Indicator Scores (0-100)'!$B$3:$B$22,0))*Methodology!$D$15 -> 6 | K8: =INDEX('Indicator Scores (0-100)'!I$3:I$22,MATCH($C8,'Indicator Scores (0-100)'!$B$3:$B$22,0))*Methodology!$D$16 -> 4.8 | L8: =INDEX('Indicator Scores (0-100)'!J$3:J$22,MATCH($C8,'Indicator Scores (0-100)'!$B$3:$B$22,0))*Methodology!$D$17 -> 5.5 | M8: =INDEX('Indicator Scores (0-100)'!K$3:K$22,MATCH($C8,'Indicator Scores (0-100)'!$B$3:$B$22,0))*Methodology!$D$18 -> 6.3 | N8: =SUM(E8:M8) -> 69.85
B9: =RANK(N9,$N$3:$N$22) -> 8 | C9: Cox's Bazar | D9: Chattogram | E9: =INDEX('Indicator Scores (0-100)'!C$3:C$22,MATCH($C9,'Indicator Scores (0-100)'!$B$3:$B$22,0))*Methodology!$D$10 -> 11.25 | F9: =INDEX('Indicator Scores (0-100)'!D$3:D$22,MATCH($C9,'Indicator Scores (0-100)'!$B$3:$B$22,0))*Methodology!$D$11 -> 12.75 | G9: =INDEX('Indicator Scores (0-100)'!E$3:E$22,MATCH($C9,'Indicator Scores (0-100)'!$B$3:$B$22,0))*Methodology!$D$12 -> 10.5 | H9: =INDEX('Indicator Scores (0-100)'!F$3:F$22,MATCH($C9,'Indicator Scores (0-100)'!$B$3:$B$22,0))*Methodology!$D$13 -> 6.6 | I9: =INDEX('Indicator Scores (0-100)'!G$3:G$22,MATCH($C9,'Indicator Scores (0-100)'!$B$3:$B$22,0))*Methodology!$D$14 -> 4 | J9: =INDEX('Indicator Scores (0-100)'!H$3:H$22,MATCH($C9,'Indicator Scores (0-100)'!$B$3:$B$22,0))*Methodology!$D$15 -> 5.5 | K9: =INDEX('Indicator Scores (0-100)'!I$3:I$22,MATCH($C9,'Indicator Scores (0-100)'!$B$3:$B$22,0))*Methodology!$D$16 -> 4.4 | L9: =INDEX('Indicator Scores (0-100)'!J$3:J$22,MATCH($C9,'Indicator Scores (0-100)'!$B$3:$B$22,0))*Methodology!$D$17 -> 4.5 | M9: =INDEX('Indicator Scores (0-100)'!K$3:K$22,MATCH($C9,'Indicator Scores (0-100)'!$B$3:$B$22,0))*Methodology!$D$18 -> 6.3 | N9: =SUM(E9:M9) -> 65.8
B10: =RANK(N10,$N$3:$N$22) -> 13 | C10: Narsingdi | D10: Dhaka | E10: =INDEX('Indicator Scores (0-100)'!C$3:C$22,MATCH($C10,'Indicator Scores (0-100)'!$B$3:$B$22,0))*Methodology!$D$10 -> 9.75 | F10: =INDEX('Indicator Scores (0-100)'!D$3:D$22,MATCH($C10,'Indicator Scores (0-100)'!$B$3:$B$22,0))*Methodology!$D$11 -> 4.5 | G10: =INDEX('Indicator Scores (0-100)'!E$3:E$22,MATCH($C10,'Indicator Scores (0-100)'!$B$3:$B$22,0))*Methodology!$D$12 -> 9.75 | H10: =INDEX('Indicator Scores (0-100)'!F$3:F$22,MATCH($C10,'Indicator Scores (0-100)'!$B$3:$B$22,0))*Methodology!$D$13 -> 7.8 | I10: =INDEX('Indicator Scores (0-100)'!G$3:G$22,MATCH($C10,'Indicator Scores (0-100)'!$B$3:$B$22,0))*Methodology!$D$14 -> 4.4 | J10: =INDEX('Indicator Scores (0-100)'!H$3:H$22,MATCH($C10,'Indicator Scores (0-100)'!$B$3:$B$22,0))*Methodology!$D$15 -> 5.5 | K10: =INDEX('Indicator Scores (0-100)'!I$3:I$22,MATCH($C10,'Indicator Scores (0-100)'!$B$3:$B$22,0))*Methodology!$D$16 -> 4.8 | L10: =INDEX('Indicator Scores (0-100)'!J$3:J$22,MATCH($C10,'Indicator Scores (0-100)'!$B$3:$B$22,0))*Methodology!$D$17 -> 6.5 | M10: =INDEX('Indicator Scores (0-100)'!K$3:K$22,MATCH($C10,'Indicator Scores (0-100)'!$B$3:$B$22,0))*Methodology!$D$18 -> 3.85 | N10: =SUM(E10:M10) -> 56.85
B11: =RANK(N11,$N$3:$N$22) -> 10 | C11: Munshiganj | D11: Dhaka | E11: =INDEX('Indicator Scores (0-100)'!C$3:C$22,MATCH($C11,'Indicator Scores (0-100)'!$B$3:$B$22,0))*Methodology!$D$10 -> 10.5 | F11: =INDEX('Indicator Scores (0-100)'!D$3:D$22,MATCH($C11,'Indicator Scores (0-100)'!$B$3:$B$22,0))*Methodology!$D$11 -> 9 | G11: =INDEX('Indicator Scores (0-100)'!E$3:E$22,MATCH($C11,'Indicator Scores (0-100)'!$B$3:$B$22,0))*Methodology!$D$12 -> 10.5 | H11: =INDEX('Indicator Scores (0-100)'!F$3:F$22,MATCH($C11,'Indicator Scores (0-100)'!$B$3:$B$22,0))*Methodology!$D$13 -> 6.6 | I11: =INDEX('Indicator Scores (0-100)'!G$3:G$22,MATCH($C11,'Indicator Scores (0-100)'!$B$3:$B$22,0))*Methodology!$D$14 -> 4.8 | J11: =INDEX('Indicator Scores (0-100)'!H$3:H$22,MATCH($C11,'Indicator Scores (0-100)'!$B$3:$B$22,0))*Methodology!$D$15 -> 5.5 | K11: =INDEX('Indicator Scores (0-100)'!I$3:I$22,MATCH($C11,'Indicator Scores (0-100)'!$B$3:$B$22,0))*Methodology!$D$16 -> 4.8 | L11: =INDEX('Indicator Scores (0-100)'!J$3:J$22,MATCH($C11,'Indicator Scores (0-100)'!$B$3:$B$22,0))*Methodology!$D$17 -> 5.5 | M11: =INDEX('Indicator Scores (0-100)'!K$3:K$22,MATCH($C11,'Indicator Scores (0-100)'!$B$3:$B$22,0))*Methodology!$D$18 -> 5.25 | N11: =SUM(E11:M11) -> 62.45
B12: =RANK(N12,$N$3:$N$22) -> 17 | C12: Tangail | D12: Dhaka | E12: =INDEX('Indicator Scores (0-100)'!C$3:C$22,MATCH($C12,'Indicator Scores (0-100)'!$B$3:$B$22,0))*Methodology!$D$10 -> 8.25 | F12: =INDEX('Indicator Scores (0-100)'!D$3:D$22,MATCH($C12,'Indicator Scores (0-100)'!$B$3:$B$22,0))*Methodology!$D$11 -> 3.75 | G12: =INDEX('Indicator Scores (0-100)'!E$3:E$22,MATCH($C12,'Indicator Scores (0-100)'!$B$3:$B$22,0))*Methodology!$D$12 -> 9 | H12: =INDEX('Indicator Scores (0-100)'!F$3:F$22,MATCH($C12,'Indicator Scores (0-100)'!$B$3:$B$22,0))*Methodology!$D$13 -> 6.6 | I12: =INDEX('Indicator Scores (0-100)'!G$3:G$22,MATCH($C12,'Indicator Scores (0-100)'!$B$3:$B$22,0))*Methodology!$D$14 -> 4 | J12: =INDEX('Indicator Scores (0-100)'!H$3:H$22,MATCH($C12,'Indicator Scores (0-100)'!$B$3:$B$22,0))*Methodology!$D$15 -> 5.5 | K12: =INDEX('Indicator Scores (0-100)'!I$3:I$22,MATCH($C12,'Indicator Scores (0-100)'!$B$3:$B$22,0))*Methodology!$D$16 -> 4.4 | L12: =INDEX('Indicator Scores (0-100)'!J$3:J$22,MATCH($C12,'Indicator Scores (0-100)'!$B$3:$B$22,0))*Methodology!$D$17 -> 5 | M12: =INDEX('Indicator Scores (0-100)'!K$3:K$22,MATCH($C12,'Indicator Scores (0-100)'!$B$3:$B$22,0))*Methodology!$D$18 -> 3.15 | N12: =SUM(E12:M12) -> 49.65
B13: =RANK(N13,$N$3:$N$22) -> 15 | C13: Bogura | D13: Rajshahi | E13: =INDEX('Indicator Scores (0-100)'!C$3:C$22,MATCH($C13,'Indicator Scores (0-100)'!$B$3:$B$22,0))*Methodology!$D$10 -> 7.5 | F13: =INDEX('Indicator Scores (0-100)'!D$3:D$22,MATCH($C13,'Indicator Scores (0-100)'!$B$3:$B$22,0))*Methodology!$D$11 -> 3 | G13: =INDEX('Indicator Scores (0-100)'!E$3:E$22,MATCH($C13,'Indicator Scores (0-100)'!$B$3:$B$22,0))*Methodology!$D$12 -> 8.25 | H13: =INDEX('Indicator Scores (0-100)'!F$3:F$22,MATCH($C13,'Indicator Scores (0-100)'!$B$3:$B$22,0))*Methodology!$D$13 -> 7.2 | I13: =INDEX('Indicator Scores (0-100)'!G$3:G$22,MATCH($C13,'Indicator Scores (0-100)'!$B$3:$B$22,0))*Methodology!$D$14 -> 4.8 | J13: =INDEX('Indicator Scores (0-100)'!H$3:H$22,MATCH($C13,'Indicator Scores (0-100)'!$B$3:$B$22,0))*Methodology!$D$15 -> 6.5 | K13: =INDEX('Indicator Scores (0-100)'!I$3:I$22,MATCH($C13,'Indicator Scores (0-100)'!$B$3:$B$22,0))*Methodology!$D$16 -> 4.8 | L13: =INDEX('Indicator Scores (0-100)'!J$3:J$22,MATCH($C13,'Indicator Scores (0-100)'!$B$3:$B$22,0))*Methodology!$D$17 -> 5.5 | M13: =INDEX('Indicator Scores (0-100)'!K$3:K$22,MATCH($C13,'Indicator Scores (0-100)'!$B$3:$B$22,0))*Methodology!$D$18 -> 4.2 | N13: =SUM(E13:M13) -> 51.75
B14: =RANK(N14,$N$3:$N$22) -> 18 | C14: Rajshahi | D14: Rajshahi | E14: =INDEX('Indicator Scores (0-100)'!C$3:C$22,MATCH($C14,'Indicator Scores (0-100)'!$B$3:$B$22,0))*Methodology!$D$10 -> 6.75 | F14: =INDEX('Indicator Scores (0-100)'!D$3:D$22,MATCH($C14,'Indicator Scores (0-100)'!$B$3:$B$22,0))*Methodology!$D$11 -> 3.75 | G14: =INDEX('Indicator Scores (0-100)'!E$3:E$22,MATCH($C14,'Indicator Scores (0-100)'!$B$3:$B$22,0))*Methodology!$D$12 -> 6 | H14: =INDEX('Indicator Scores (0-100)'!F$3:F$22,MATCH($C14,'Indicator Scores (0-100)'!$B$3:$B$22,0))*Methodology!$D$13 -> 6.6 | I14: =INDEX('Indicator Scores (0-100)'!G$3:G$22,MATCH($C14,'Indicator Scores (0-100)'!$B$3:$B$22,0))*Methodology!$D$14 -> 5.2 | J14: =INDEX('Indicator Scores (0-100)'!H$3:H$22,MATCH($C14,'Indicator Scores (0-100)'!$B$3:$B$22,0))*Methodology!$D$15 -> 7 | K14: =INDEX('Indicator Scores (0-100)'!I$3:I$22,MATCH($C14,'Indicator Scores (0-100)'!$B$3:$B$22,0))*Methodology!$D$16 -> 5.2 | L14: =INDEX('Indicator Scores (0-100)'!J$3:J$22,MATCH($C14,'Indicator Scores (0-100)'!$B$3:$B$22,0))*Methodology!$D$17 -> 4 | M14: =INDEX('Indicator Scores (0-100)'!K$3:K$22,MATCH($C14,'Indicator Scores (0-100)'!$B$3:$B$22,0))*Methodology!$D$18 -> 2.8 | N14: =SUM(E14:M14) -> 47.3
... B22: =RANK(N22,$N$3:$N$22) -> 14 | C22: Faridpur | D22: Dhaka | E22: =INDEX('Indicator Scores (0-100)'!C$3:C$22,MATCH($C22,'Indicator Scores (0-100)'!$B$3:$B$22,0))*Methodology!$D$10 -> 9 | F22: =INDEX('Indicator Scores (0-100)'!D$3:D$22,MATCH($C22,'Indicator Scores (0-100)'!$B$3:$B$22,0))*Methodology!$D$11 -> 4.5 | G22: =INDEX('Indicator Scores (0-100)'!E$3:E$22,MATCH($C22,'Indicator Scores (0-100)'!$B$3:$B$22,0))*Methodology!$D$12 -> 9 | H22: =INDEX('Indicator Scores (0-100)'!F$3:F$22,MATCH($C22,'Indicator Scores (0-100)'!$B$3:$B$22,0))*Methodology!$D$13 -> 6.6 | I22: =INDEX('Indicator Scores (0-100)'!G$3:G$22,MATCH($C22,'Indicator Scores (0-100)'!$B$3:$B$22,0))*Methodology!$D$14 -> 4.4 | J22: =INDEX('Indicator Scores (0-100)'!H$3:H$22,MATCH($C22,'Indicator Scores (0-100)'!$B$3:$B$22,0))*Methodology!$D$15 -> 5.5 | K22: =INDEX('Indicator Scores (0-100)'!I$3:I$22,MATCH($C22,'Indicator Scores (0-100)'!$B$3:$B$22,0))*Methodology!$D$16 -> 4.4 | L22: =INDEX('Indicator Scores (0-100)'!J$3:J$22,MATCH($C22,'Indicator Scores (0-100)'!$B$3:$B$22,0))*Methodology!$D$17 -> 4.5 | M22: =INDEX('Indicator Scores (0-100)'!K$3:K$22,MATCH($C22,'Indicator Scores (0-100)'!$B$3:$B$22,0))*Methodology!$D$18 -> 4.2 | N22: =SUM(E22:M22) -> 52.1
C24: Composite Score = sum of (indicator score x indicator weight), looked up by district NAME via INDEX/MATCH (robust to reordering). Weights are set on the 'Methodology' sheet; indicator scores are set on the 'Indicator Scores (0-100)' sheet. Both are formula-linked, so changing either recalculates rank automatically. See the 'Formula Guide' sheet for a full explanation and worked example.
B26: © 2026 Ahmed Safwan Sajid. All Rights Reserved. Intellectual Property of the Author.

Sheet Sensitivity Analysis
B2: Sensitivity Analysis — How Robust Is the Ranking to Different Weighting Philosophies?
B3: The Methodology sheet's weights reflect one reasonable view of what matters most. This sheet re-runs the entire index under four alternative, equally defensible weighting philosophies, so the ranking's sensitivity to that judgment call is visible and testable rather than hidden inside one fixed set of numbers.
B5: 1. Scenario Weight Definitions (INPUT CELLS — edit to test your own scenario)
B6: Scenario | C6: Connectivity | D6: EPZ / Econ. Zone | E6: Power/Gas Reliability | F6: Labor Availability | G6: Literacy/Tech Ed. | H6: Banking Density | I6: Broadband/Mobile | J6: Industrial Base | K6: Investment Momentum | L6: Total
B7: Base Case (current model) | C7: 0.15 | D7: 0.15 | E7: 0.15 | F7: 0.12 | G7: 0.08 | H7: 0.1 | I7: 0.08 | J7: 0.1 | K7: 0.07 | L7: =SUM(C7:K7) -> 1
B8: Equal Weights | C8: 0.1111 | D8: 0.1111 | E8: 0.1111 | F8: 0.1111 | G8: 0.1111 | H8: 0.1111 | I8: 0.1111 | J8: 0.1111 | K8: 0.1111 | L8: =SUM(C8:K8) -> 0.9999
B9: Infrastructure-Heavy | C9: 0.2 | D9: 0.2 | E9: 0.2 | F9: 0.08 | G9: 0.05 | H9: 0.07 | I9: 0.05 | J9: 0.1 | K9: 0.05 | L9: =SUM(C9:K9) -> 1
B10: Labor/Education-Heavy | C10: 0.12 | D10: 0.12 | E10: 0.12 | F10: 0.2 | G10: 0.15 | H10: 0.08 | I10: 0.06 | J10: 0.1 | K10: 0.05 | L10: =SUM(C10:K10) -> 1
B11: Investment-Momentum-Heavy (forward-looking) | C11: 0.13 | D11: 0.18 | E11: 0.13 | F11: 0.1 | G11: 0.06 | H11: 0.08 | I11: 0.06 | J11: 0.06 | K11: 0.2 | L11: =SUM(C11:K11) -> 1
B14: 2. Composite Score and Rank Per District, Under Each Scenario
B15: District | C15: Base Case Score | D15: Base Case Rank | E15: Equal Weights Score | F15: Equal Weights Rank | G15: Infrastructure-Heavy Score | H15: Infrastructure-Heavy Rank | I15: Labor/Education-Heavy Score | J15: Labor/Education-Heavy Rank | K15: Investment-Momentum-Heavy Score | L15: Investment-Momentum-Heavy Rank | M15: Min Rank | N15: Max Rank | O15: Rank Range | P15: Stability
B16: Dhaka | C16: =SUMPRODUCT(INDEX('Indicator Scores (0-100)'!$C$3:$K$22,MATCH($B16,'Indicator Scores (0-100)'!$B$3:$B$22,0),0),$C$7:$K$7) -> 89.6 | D16: =RANK(C16,$C$16:$C$35) -> 1 | E16: =SUMPRODUCT(INDEX('Indicator Scores (0-100)'!$C$3:$K$22,MATCH($B16,'Indicator Scores (0-100)'!$B$3:$B$22,0),0),$C$8:$K$8) -> 88.88 | F16: =RANK(E16,$E$16:$E$35) -> 1 | G16: =SUMPRODUCT(INDEX('Indicator Scores (0-100)'!$C$3:$K$22,MATCH($B16,'Indicator Scores (0-100)'!$B$3:$B$22,0),0),$C$9:$K$9) -> 89.85 | H16: =RANK(G16,$G$16:$G$35) -> 2 | I16: =SUMPRODUCT(INDEX('Indicator Scores (0-100)'!$C$3:$K$22,MATCH($B16,'Indicator Scores (0-100)'!$B$3:$B$22,0),0),$C$10:$K$10) -> 89.9 | J16: =RANK(I16,$I$16:$I$35) -> 1 | K16: =SUMPRODUCT(INDEX('Indicator Scores (0-100)'!$C$3:$K$22,MATCH($B16,'Indicator Scores (0-100)'!$B$3:$B$22,0),0),$C$11:$K$11) -> 86.7 | L16: =RANK(K16,$K$16:$K$35) -> 2 | M16: =MIN(D16,F16,H16,J16,L16) -> 1 | N16: =MAX(D16,F16,H16,J16,L16) -> 2 | O16: =N16-M16 -> 1 | P16: =IF(O16<=1,"Stable",IF(O16<=3,"Moderate","Volatile")) -> Stable
B17: Gazipur | C17: =SUMPRODUCT(INDEX('Indicator Scores (0-100)'!$C$3:$K$22,MATCH($B17,'Indicator Scores (0-100)'!$B$3:$B$22,0),0),$C$7:$K$7) -> 83.1 | D17: =RANK(C17,$C$16:$C$35) -> 3 | E17: =SUMPRODUCT(INDEX('Indicator Scores (0-100)'!$C$3:$K$22,MATCH($B17,'Indicator Scores (0-100)'!$B$3:$B$22,0),0),$C$8:$K$8) -> 82.214 | F17: =RANK(E17,$E$16:$E$35) -> 3 | G17: =SUMPRODUCT(INDEX('Indicator Scores (0-100)'!$C$3:$K$22,MATCH($B17,'Indicator Scores (0-100)'!$B$3:$B$22,0),0),$C$9:$K$9) -> 83.6 | H17: =RANK(G17,$G$16:$G$35) -> 3 | I17: =SUMPRODUCT(INDEX('Indicator Scores (0-100)'!$C$3:$K$22,MATCH($B17,'Indicator Scores (0-100)'!$B$3:$B$22,0),0),$C$10:$K$10) -> 83.5 | J17: =RANK(I17,$I$16:$I$35) -> 3 | K17: =SUMPRODUCT(INDEX('Indicator Scores (0-100)'!$C$3:$K$22,MATCH($B17,'Indicator Scores (0-100)'!$B$3:$B$22,0),0),$C$11:$K$11) -> 82.65 | L17: =RANK(K17,$K$16:$K$35) -> 3 | M17: =MIN(D17,F17,H17,J17,L17) -> 3 | N17: =MAX(D17,F17,H17,J17,L17) -> 3 | O17: =N17-M17 -> 0 | P17: =IF(O17<=1,"Stable",IF(O17<=3,"Moderate","Volatile")) -> Stable
B18: Narayanganj | C18: =SUMPRODUCT(INDEX('Indicator Scores (0-100)'!$C$3:$K$22,MATCH($B18,'Indicator Scores (0-100)'!$B$3:$B$22,0),0),$C$7:$K$7) -> 76.1 | D18: =RANK(C18,$C$16:$C$35) -> 4 | E18: =SUMPRODUCT(INDEX('Indicator Scores (0-100)'!$C$3:$K$22,MATCH($B18,'Indicator Scores (0-100)'!$B$3:$B$22,0),0),$C$8:$K$8) -> 74.9925 | F18: =RANK(E18,$E$16:$E$35) -> 4 | G18: =SUMPRODUCT(INDEX('Indicator Scores (0-100)'!$C$3:$K$22,MATCH($B18,'Indicator Scores (0-100)'!$B$3:$B$22,0),0),$C$9:$K$9) -> 76.55 | H18: =RANK(G18,$G$16:$G$35) -> 4 | I18: =SUMPRODUCT(INDEX('Indicator Scores (0-100)'!$C$3:$K$22,MATCH($B18,'Indicator Scores (0-100)'!$B$3:$B$22,0),0),$C$10:$K$10) -> 76.35 | J18: =RANK(I18,$I$16:$I$35) -> 4 | K18: =SUMPRODUCT(INDEX('Indicator Scores (0-100)'!$C$3:$K$22,MATCH($B18,'Indicator Scores (0-100)'!$B$3:$B$22,0),0),$C$11:$K$11) -> 73.65 | L18: =RANK(K18,$K$16:$K$35) -> 5 | M18: =MIN(D18,F18,H18,J18,L18) -> 4 | N18: =MAX(D18,F18,H18,J18,L18) -> 5 | O18: =N18-M18 -> 1 | P18: =IF(O18<=1,"Stable",IF(O18<=3,"Moderate","Volatile")) -> Stable
B19: Chattogram | C19: =SUMPRODUCT(INDEX('Indicator Scores (0-100)'!$C$3:$K$22,MATCH($B19,'Indicator Scores (0-100)'!$B$3:$B$22,0),0),$C$7:$K$7) -> 89.4 | D19: =RANK(C19,$C$16:$C$35) -> 2 | E19: =SUMPRODUCT(INDEX('Indicator Scores (0-100)'!$C$3:$K$22,MATCH($B19,'Indicator Scores (0-100)'!$B$3:$B$22,0),0),$C$8:$K$8) -> 87.769 | F19: =RANK(E19,$E$16:$E$35) -> 2 | G19: =SUMPRODUCT(INDEX('Indicator Scores (0-100)'!$C$3:$K$22,MATCH($B19,'Indicator Scores (0-100)'!$B$3:$B$22,0),0),$C$9:$K$9) -> 91.35 | H19: =RANK(G19,$G$16:$G$35) -> 1 | I19: =SUMPRODUCT(INDEX('Indicator Scores (0-100)'!$C$3:$K$22,MATCH($B19,'Indicator Scores (0-100)'!$B$3:$B$22,0),0),$C$10:$K$10) -> 87.45 | J19: =RANK(I19,$I$16:$I$35) -> 2 | K19: =SUMPRODUCT(INDEX('Indicator Scores (0-100)'!$C$3:$K$22,MATCH($B19,'Indicator Scores (0-100)'!$B$3:$B$22,0),0),$C$11:$K$11) -> 89.45 | L19: =RANK(K19,$K$16:$K$35) -> 1 | M19: =MIN(D19,F19,H19,J19,L19) -> 1 | N19: =MAX(D19,F19,H19,J19,L19) -> 2 | O19: =N19-M19 -> 1 | P19: =IF(O19<=1,"Stable",IF(O19<=3,"Moderate","Volatile")) -> Stable
B20: Cumilla | C20: =SUMPRODUCT(INDEX('Indicator Scores (0-100)'!$C$3:$K$22,MATCH($B20,'Indicator Scores (0-100)'!$B$3:$B$22,0),0),$C$7:$K$7) -> 67.2 | D20: =RANK(C20,$C$16:$C$35) -> 6 | E20: =SUMPRODUCT(INDEX('Indicator Scores (0-100)'!$C$3:$K$22,MATCH($B20,'Indicator Scores (0-100)'!$B$3:$B$22,0),0),$C$8:$K$8) -> 66.66 | F20: =RANK(E20,$E$16:$E$35) -> 6 | G20: =SUMPRODUCT(INDEX('Indicator Scores (0-100)'!$C$3:$K$22,MATCH($B20,'Indicator Scores (0-100)'!$B$3:$B$22,0),0),$C$9:$K$9) -> 67.65 | H20: =RANK(G20,$G$16:$G$35) -> 7 | I20: =SUMPRODUCT(INDEX('Indicator Scores (0-100)'!$C$3:$K$22,MATCH($B20,'Indicator Scores (0-100)'!$B$3:$B$22,0),0),$C$10:$K$10) -> 66.95 | J20: =RANK(I20,$I$16:$I$35) -> 6 | K20: =SUMPRODUCT(INDEX('Indicator Scores (0-100)'!$C$3:$K$22,MATCH($B20,'Indicator Scores (0-100)'!$B$3:$B$22,0),0),$C$11:$K$11) -> 67.55 | L20: =RANK(K20,$K$16:$K$35) -> 8 | M20: =MIN(D20,F20,H20,J20,L20) -> 6 | N20: =MAX(D20,F20,H20,J20,L20) -> 8 | O20: =N20-M20 -> 2 | P20: =IF(O20<=1,"Stable",IF(O20<=3,"Moderate","Volatile")) -> Moderate
B21: Feni | C21: =SUMPRODUCT(INDEX('Indicator Scores (0-100)'!$C$3:$K$22,MATCH($B21,'Indicator Scores (0-100)'!$B$3:$B$22,0),0),$C$7:$K$7) -> 69.85 | D21: =RANK(C21,$C$16:$C$35) -> 5 | E21: =SUMPRODUCT(INDEX('Indicator Scores (0-100)'!$C$3:$K$22,MATCH($B21,'Indicator Scores (0-100)'!$B$3:$B$22,0),0),$C$8:$K$8) -> 68.882 | F21: =RANK(E21,$E$16:$E$35) -> 5 | G21: =SUMPRODUCT(INDEX('Indicator Scores (0-100)'!$C$3:$K$22,MATCH($B21,'Indicator Scores (0-100)'!$B$3:$B$22,0),0),$C$9:$K$9) -> 72 | H21: =RANK(G21,$G$16:$G$35) -> 5 | I21: =SUMPRODUCT(INDEX('Indicator Scores (0-100)'!$C$3:$K$22,MATCH($B21,'Indicator Scores (0-100)'!$B$3:$B$22,0),0),$C$10:$K$10) -> 67.6 | J21: =RANK(I21,$I$16:$I$35) -> 5 | K21: =SUMPRODUCT(INDEX('Indicator Scores (0-100)'!$C$3:$K$22,MATCH($B21,'Indicator Scores (0-100)'!$B$3:$B$22,0),0),$C$11:$K$11) -> 74.35 | L21: =RANK(K21,$K$16:$K$35) -> 4 | M21: =MIN(D21,F21,H21,J21,L21) -> 4 | N21: =MAX(D21,F21,H21,J21,L21) -> 5 | O21: =N21-M21 -> 1 | P21: =IF(O21<=1,"Stable",IF(O21<=3,"Moderate","Volatile")) -> Stable
B22: Cox's Bazar | C22: =SUMPRODUCT(INDEX('Indicator Scores (0-100)'!$C$3:$K$22,MATCH($B22,'Indicator Scores (0-100)'!$B$3:$B$22,0),0),$C$7:$K$7) -> 65.8 | D22: =RANK(C22,$C$16:$C$35) -> 8 | E22: =SUMPRODUCT(INDEX('Indicator Scores (0-100)'!$C$3:$K$22,MATCH($B22,'Indicator Scores (0-100)'!$B$3:$B$22,0),0),$C$8:$K$8) -> 64.438 | F22: =RANK(E22,$E$16:$E$35) -> 9 | G22: =SUMPRODUCT(INDEX('Indicator Scores (0-100)'!$C$3:$K$22,MATCH($B22,'Indicator Scores (0-100)'!$B$3:$B$22,0),0),$C$9:$K$9) -> 68.5 | H22: =RANK(G22,$G$16:$G$35) -> 6 | I22: =SUMPRODUCT(INDEX('Indicator Scores (0-100)'!$C$3:$K$22,MATCH($B22,'Indicator Scores (0-100)'!$B$3:$B$22,0),0),$C$10:$K$10) -> 62.8 | J22: =RANK(I22,$I$16:$I$35) -> 9 | K22: =SUMPRODUCT(INDEX('Indicator Scores (0-100)'!$C$3:$K$22,MATCH($B22,'Indicator Scores (0-100)'!$B$3:$B$22,0),0),$C$11:$K$11) -> 71.05 | L22: =RANK(K22,$K$16:$K$35) -> 6 | M22: =MIN(D22,F22,H22,J22,L22) -> 6 | N22: =MAX(D22,F22,H22,J22,L22) -> 9 | O22: =N22-M22 -> 3 | P22: =IF(O22<=1,"Stable",IF(O22<=3,"Moderate","Volatile")) -> Moderate
B23: Narsingdi | C23: =SUMPRODUCT(INDEX('Indicator Scores (0-100)'!$C$3:$K$22,MATCH($B23,'Indicator Scores (0-100)'!$B$3:$B$22,0),0),$C$7:$K$7) -> 56.85 | D23: =RANK(C23,$C$16:$C$35) -> 13 | E23: =SUMPRODUCT(INDEX('Indicator Scores (0-100)'!$C$3:$K$22,MATCH($B23,'Indicator Scores (0-100)'!$B$3:$B$22,0),0),$C$8:$K$8) -> 57.2165 | F23: =RANK(E23,$E$16:$E$35) -> 13 | G23: =SUMPRODUCT(INDEX('Indicator Scores (0-100)'!$C$3:$K$22,MATCH($B23,'Indicator Scores (0-100)'!$B$3:$B$22,0),0),$C$9:$K$9) -> 56.05 | H23: =RANK(G23,$G$16:$G$35) -> 13 | I23: =SUMPRODUCT(INDEX('Indicator Scores (0-100)'!$C$3:$K$22,MATCH($B23,'Indicator Scores (0-100)'!$B$3:$B$22,0),0),$C$10:$K$10) -> 57.7 | J23: =RANK(I23,$I$16:$I$35) -> 13 | K23: =SUMPRODUCT(INDEX('Indicator Scores (0-100)'!$C$3:$K$22,MATCH($B23,'Indicator Scores (0-100)'!$B$3:$B$22,0),0),$C$11:$K$11) -> 55 | L23: =RANK(K23,$K$16:$K$35) -> 13 | M23: =MIN(D23,F23,H23,J23,L23) -> 13 | N23: =MAX(D23,F23,H23,J23,L23) -> 13 | O23: =N23-M23 -> 0 | P23: =IF(O23<=1,"Stable",IF(O23<=3,"Moderate","Volatile")) -> Stable
B24: Munshiganj | C24: =SUMPRODUCT(INDEX('Indicator Scores (0-100)'!$C$3:$K$22,MATCH($B24,'Indicator Scores (0-100)'!$B$3:$B$22,0),0),$C$7:$K$7) -> 62.45 | D24: =RANK(C24,$C$16:$C$35) -> 10 | E24: =SUMPRODUCT(INDEX('Indicator Scores (0-100)'!$C$3:$K$22,MATCH($B24,'Indicator Scores (0-100)'!$B$3:$B$22,0),0),$C$8:$K$8) -> 62.216 | F24: =RANK(E24,$E$16:$E$35) -> 10 | G24: =SUMPRODUCT(INDEX('Indicator Scores (0-100)'!$C$3:$K$22,MATCH($B24,'Indicator Scores (0-100)'!$B$3:$B$22,0),0),$C$9:$K$9) -> 63.5 | H24: =RANK(G24,$G$16:$G$35) -> 10 | I24: =SUMPRODUCT(INDEX('Indicator Scores (0-100)'!$C$3:$K$22,MATCH($B24,'Indicator Scores (0-100)'!$B$3:$B$22,0),0),$C$10:$K$10) -> 61.25 | J24: =RANK(I24,$I$16:$I$35) -> 11 | K24: =SUMPRODUCT(INDEX('Indicator Scores (0-100)'!$C$3:$K$22,MATCH($B24,'Indicator Scores (0-100)'!$B$3:$B$22,0),0),$C$11:$K$11) -> 64.4 | L24: =RANK(K24,$K$16:$K$35) -> 9 | M24: =MIN(D24,F24,H24,J24,L24) -> 9 | N24: =MAX(D24,F24,H24,J24,L24) -> 11 | O24: =N24-M24 -> 2 | P24: =IF(O24<=1,"Stable",IF(O24<=3,"Moderate","Volatile")) -> Moderate
B25: Tangail | C25: =SUMPRODUCT(INDEX('Indicator Scores (0-100)'!$C$3:$K$22,MATCH($B25,'Indicator Scores (0-100)'!$B$3:$B$22,0),0),$C$7:$K$7) -> 49.65 | D25: =RANK(C25,$C$16:$C$35) -> 17 | E25: =SUMPRODUCT(INDEX('Indicator Scores (0-100)'!$C$3:$K$22,MATCH($B25,'Indicator Scores (0-100)'!$B$3:$B$22,0),0),$C$8:$K$8) -> 49.995 | F25: =RANK(E25,$E$16:$E$35) -> 17 | G25: =SUMPRODUCT(INDEX('Indicator Scores (0-100)'!$C$3:$K$22,MATCH($B25,'Indicator Scores (0-100)'!$B$3:$B$22,0),0),$C$9:$K$9) -> 48.75 | H25: =RANK(G25,$G$16:$G$35) -> 17 | I25: =SUMPRODUCT(INDEX('Indicator Scores (0-100)'!$C$3:$K$22,MATCH($B25,'Indicator Scores (0-100)'!$B$3:$B$22,0),0),$C$10:$K$10) -> 50.25 | J25: =RANK(I25,$I$16:$I$35) -> 17 | K25: =SUMPRODUCT(INDEX('Indicator Scores (0-100)'!$C$3:$K$22,MATCH($B25,'Indicator Scores (0-100)'!$B$3:$B$22,0),0),$C$11:$K$11) -> 47.65 | L25: =RANK(K25,$K$16:$K$35) -> 17 | M25: =MIN(D25,F25,H25,J25,L25) -> 17 | N25: =MAX(D25,F25,H25,J25,L25) -> 17 | O25: =N25-M25 -> 0 | P25: =IF(O25<=1,"Stable",IF(O25<=3,"Moderate","Volatile")) -> Stable
B26: Bogura | C26: =SUMPRODUCT(INDEX('Indicator Scores (0-100)'!$C$3:$K$22,MATCH($B26,'Indicator Scores (0-100)'!$B$3:$B$22,0),0),$C$7:$K$7) -> 51.75 | D26: =RANK(C26,$C$16:$C$35) -> 15 | E26: =SUMPRODUCT(INDEX('Indicator Scores (0-100)'!$C$3:$K$22,MATCH($B26,'Indicator Scores (0-100)'!$B$3:$B$22,0),0),$C$8:$K$8) -> 53.8835 | F26: =RANK(E26,$E$16:$E$35) -> 14 | G26: =SUMPRODUCT(INDEX('Indicator Scores (0-100)'!$C$3:$K$22,MATCH($B26,'Indicator Scores (0-100)'!$B$3:$B$22,0),0),$C$9:$K$9) -> 48.85 | H26: =RANK(G26,$G$16:$G$35) -> 16 | I26: =SUMPRODUCT(INDEX('Indicator Scores (0-100)'!$C$3:$K$22,MATCH($B26,'Indicator Scores (0-100)'!$B$3:$B$22,0),0),$C$10:$K$10) -> 53.3 | J26: =RANK(I26,$I$16:$I$35) -> 14 | K26: =SUMPRODUCT(INDEX('Indicator Scores (0-100)'!$C$3:$K$22,MATCH($B26,'Indicator Scores (0-100)'!$B$3:$B$22,0),0),$C$11:$K$11) -> 50.95 | L26: =RANK(K26,$K$16:$K$35) -> 16 | M26: =MIN(D26,F26,H26,J26,L26) -> 14 | N26: =MAX(D26,F26,H26,J26,L26) -> 16 | O26: =N26-M26 -> 2 | P26: =IF(O26<=1,"Stable",IF(O26<=3,"Moderate","Volatile")) -> Moderate
B27: Rajshahi | C27: =SUMPRODUCT(INDEX('Indicator Scores (0-100)'!$C$3:$K$22,MATCH($B27,'Indicator Scores (0-100)'!$B$3:$B$22,0),0),$C$7:$K$7) -> 47.3 | D27: =RANK(C27,$C$16:$C$35) -> 18 | E27: =SUMPRODUCT(INDEX('Indicator Scores (0-100)'!$C$3:$K$22,MATCH($B27,'Indicator Scores (0-100)'!$B$3:$B$22,0),0),$C$8:$K$8) -> 49.4395 | F27: =RANK(E27,$E$16:$E$35) -> 18 | G27: =SUMPRODUCT(INDEX('Indicator Scores (0-100)'!$C$3:$K$22,MATCH($B27,'Indicator Scores (0-100)'!$B$3:$B$22,0),0),$C$9:$K$9) -> 43.8 | H27: =RANK(G27,$G$16:$G$35) -> 18 | I27: =SUMPRODUCT(INDEX('Indicator Scores (0-100)'!$C$3:$K$22,MATCH($B27,'Indicator Scores (0-100)'!$B$3:$B$22,0),0),$C$10:$K$10) -> 49.45 | J27: =RANK(I27,$I$16:$I$35) -> 18 | K27: =SUMPRODUCT(INDEX('Indicator Scores (0-100)'!$C$3:$K$22,MATCH($B27,'Indicator Scores (0-100)'!$B$3:$B$22,0),0),$C$11:$K$11) -> 44.85 | L27: =RANK(K27,$K$16:$K$35) -> 18 | M27: =MIN(D27,F27,H27,J27,L27) -> 18 | N27: =MAX(D27,F27,H27,J27,L27) -> 18 | O27: =N27-M27 -> 0 | P27: =IF(O27<=1,"Stable",IF(O27<=3,"Moderate","Volatile")) -> Stable
... B35: Faridpur | C35: =SUMPRODUCT(INDEX('Indicator Scores (0-100)'!$C$3:$K$22,MATCH($B35,'Indicator Scores (0-100)'!$B$3:$B$22,0),0),$C$7:$K$7) -> 52.1 | D35: =RANK(C35,$C$16:$C$35) -> 14 | E35: =SUMPRODUCT(INDEX('Indicator Scores (0-100)'!$C$3:$K$22,MATCH($B35,'Indicator Scores (0-100)'!$B$3:$B$22,0),0),$C$8:$K$8) -> 52.7725 | F35: =RANK(E35,$E$16:$E$35) -> 15 | G35: =SUMPRODUCT(INDEX('Indicator Scores (0-100)'!$C$3:$K$22,MATCH($B35,'Indicator Scores (0-100)'!$B$3:$B$22,0),0),$C$9:$K$9) -> 51.25 | H35: =RANK(G35,$G$16:$G$35) -> 14 | I35: =SUMPRODUCT(INDEX('Indicator Scores (0-100)'!$C$3:$K$22,MATCH($B35,'Indicator Scores (0-100)'!$B$3:$B$22,0),0),$C$10:$K$10) -> 52.45 | J35: =RANK(I35,$I$16:$I$35) -> 15 | K35: =SUMPRODUCT(INDEX('Indicator Scores (0-100)'!$C$3:$K$22,MATCH($B35,'Indicator Scores (0-100)'!$B$3:$B$22,0),0),$C$11:$K$11) -> 52.2 | L35: =RANK(K35,$K$16:$K$35) -> 15 | M35: =MIN(D35,F35,H35,J35,L35) -> 14 | N35: =MAX(D35,F35,H35,J35,L35) -> 15 | O35: =N35-M35 -> 1 | P35: =IF(O35<=1,"Stable",IF(O35<=3,"Moderate","Volatile")) -> Stable
B37: How to read this: "Rank Range" is the spread between a district's best and worst rank across the five scenarios above. "Stable" (range 0-1) means the district lands in essentially the same position regardless of weighting philosophy — a robust conclusion. "Volatile" (range 4+) means the district's position depends heavily on which factors you choose to prioritize, and any decision resting on that district's specific rank should be revisited under the scenario closest to your actual priorities. To test a scenario of your own, edit any weight row in Section 1 (each row must still sum to 100%) — every score and rank in Section 2 recalculates automatically.
B42: © 2026 Ahmed Safwan Sajid. All Rights Reserved. Intellectual Property of the Author.

Sheet Source Log
B1: Source Log — Key Evidence Per District
B2: District | C2: Indicator(s) | D2: Key Fact / Statistic | E2: Source | F2: Year
B3: Dhaka | C3: Industrial Base | D3: Manufacturing contributes 56% of Dhaka District GDP (2025); RMG is the primary driver. | E3: Grokipedia / Dhaka District (cites BBS PHC 2021-22 District Report) | F3: 2025
B4: Dhaka | C4: Literacy | D4: Literacy rate 84.88% (population aged 7+). | E4: Grokipedia / Dhaka District (cites BBS District Report Dhaka, 25-06-2024) | F4: 2022
B5: Gazipur | C5: EPZ / Industrial Base | D5: BEPZ is Bangladesh's largest industrial park at 2,023 acres; hosts textiles, pharma, food processing. | E5: 'About Gazipur', industry overview | F5: 2023
B6: Gazipur | C6: Industrial Base | D6: ~75% of the country's garment industry is located in Gazipur. | E6: Industrial Engineers Association of Bangladesh (IEAB) | F6: n.d.
B7: Chattogram | C7: Connectivity | D7: Chattogram port handles 92% of Bangladesh's seaborne trade and 98% of containerised transport. | E7: The Daily Star, 'How Chattogram built its economic legacy' | F7: 2025
B8: Chattogram | C8: EPZ | D8: Chattogram EPZ (est. 1983) has grown to 144 industrial units, incl. 78 RMG factories; $1.8bn exports in 9 months. | E8: The Daily Star | F8: 2025
B9: Chattogram | C9: EPZ | D9: Karnaphuli EPZ employs 77,137 workers with $13.90bn cumulative exports. | E9: BEPZA official site (bepza.gov.bd) | F9: n.d.
B10: Narayanganj | C10: Industrial Base | D10: Accounts for 55% of national knitwear manufacturing and 33% of textile mills. | E10: ScienceDirect, 'City profile: Narayanganj, Bangladesh' (cites BBS 2013) | F10: 2016
B11: Narayanganj | C11: EPZ | D11: Adamjee EPZ attracted 46 entrepreneurs, $1.6bn+ exports, 40,000+ jobs (2014-15). | E11: ScienceDirect (cites BEPZA 2015) | F11: 2016
B12: Cumilla | C12: EPZ | D12: Cumilla EPZ employs ~50,000 people; FY2024-25 exports ~$902m, doubling original target. | E12: BSS News / New Age | F12: 2025
B13: Cumilla | C13: Connectivity | D13: 167 km from Chattogram seaport, 97 km from Dhaka; airport not operational; no direct EPZ rail spur. | E13: The Business Standard | F13: 2022
... B42: National benchmark | C42: Power/Gas | D42: National grid electrification reached 99.5% of the population (2023) — access is near-universal; reliability is the real differentiator. | E42: Wikipedia, 'Electricity sector in Bangladesh' | F42: 2023
B45: © 2026 Ahmed Safwan Sajid. All Rights Reserved. Intellectual Property of the Author.

Sheet Data Basis Notes
B1: Data Basis & Confidence Notes Per Indicator
B2: Indicator | C2: Basis for Scores / Confidence Level / Recommended Verification Source
B3: Seaport/Airport Proximity & Multimodal Connectivity | C3: Based on documented seaport/airport distances, highway/rail links, and BEZA/BEPZA site descriptions (see Source Log).
B4: EPZ / Economic Zone / Industrial Park Presence | C4: Based on confirmed BEPZA/BEZA zone presence, acreage, and operational status (see Source Log).
B5: Power & Gas Availability / Reliability | C5: National grid access is ~99.5% (BPDB, 2023) and therefore not differentiating; score reflects documented INDUSTRIAL-GRADE reliability complaints/advantages per district (see Source Log). LOWER CONFIDENCE — recommend verifying against PGCB/Petrobangla district load-shedding data.
B6: Labor Force Availability & Wage Competitiveness | C6: Based on documented workforce counts in EPZs/RMG clusters and qualitative labor-supply commentary. LOWER CONFIDENCE for districts without EPZ employment figures.
B7: Literacy Rate & Technical Education Infrastructure | C7: Where exact BBS 2022 District Report figures were sourced, used directly (Dhaka, Jashore). Other districts estimated from division-level 2022 census benchmarks (Daily Star, 2023) and 2011 census data adjusted for a plausible decade of improvement. MODERATE-LOW CONFIDENCE — recommend pulling exact figures from each BBS District Report PDF.
B8: Banking & Financial Institution Presence | C8: No single public district-wise branch-count table was retrievable via web search in this session. Score is a proxy based on divisional-seat status, Bangladesh Bank physical branch presence, EPZ/industrial scale, and population size. LOW CONFIDENCE — recommend Bangladesh Bank 'Scheduled Banks Statistics' quarterly bulletin (district-wise branch tables) for exact figures.
B9: Broadband & Mobile Network Coverage | C9: No single public district-wise coverage table was retrievable via web search in this session. Score is a proxy based on divisional urban/rural mix and BBS 2022 Urban Area Report division-level internet/mobile use rates. LOW CONFIDENCE — recommend BTRC district-wise subscriber/coverage data.
B10: Existing Industrial Base (Major Industries Present) | C10: Based on documented count and scale of operating industries/factories per district (see Source Log).
B11: Recent Public/Private Investment Momentum | C11: Based on documented recent (2023-2026) investment announcements, project financing, and government/BEZA/BEPZA statements (see Source Log).
B14: © 2026 Ahmed Safwan Sajid. All Rights Reserved. Intellectual Property of the Author.

Sheet References
B1: Complete Reference List
B2: # | C2: Source
B3: 1 | C3: Bangladesh Bureau of Statistics (BBS), 'Population and Housing Census 2022: Urban Area Report', Statistics and Informatics Division, Ministry of Planning, January 2025.
B4: 2 | C4: Bangladesh Bureau of Statistics (BBS), District Reports (individual district PDFs), Population and Housing Census 2022, published June 2024.
B5: 3 | C5: The Daily Star, "Bangladesh's literacy rate now 74.66%", 2022.
B6: 4 | C6: The Daily Star, "How Chattogram built its economic legacy", 16 May 2025.
B7: 5 | C7: The Daily Star, "Narsingdi's clout as industrial hub grows", 2023.
B8: 6 | C8: The Daily Star, "Bepza secures land to set up Jashore EPZ", 24 March 2024.
B9: 7 | C9: The Daily Star, "Rajshahi to get economic zone by 2019".
B10: 8 | C10: The Daily Star, "Red tape delays construction of second economic zone in Rangpur", 18 March 2024.
B11: 9 | C11: The Business Standard (TBS), "With favourable environment, export industries still missing in Cumilla", 7 August 2022.
B12: 10 | C12: The Business Standard (TBS), "Cox's Bazar: An economic game-changer in the making", 4 July 2021.
B13: 11 | C13: The Business Standard (TBS), "Unavailability of fuel major obstacle to industrialisation in Khulna region", 4 February 2022.
B14: 12 | C14: The Business Standard (TBS), "One year of Padma Bridge: A new dawn begins to shine", 26 June 2023.
... B32: 30 | C32: Inspira Advisory and Consulting Ltd., "Economic Dynamics of Cox's Bazar: Sectoral Insights of the Region", 27 July 2025.
B35: © 2026 Ahmed Safwan Sajid. All Rights Reserved. Intellectual Property of the Author.
